Pokekachu/__int__.py
Pokekachu/pokemon.csv
Pokekachu/random_pokemon.py
Pokekachu-1.0.1.dist-info/METADATA
Pokekachu-1.0.1.dist-info/WHEEL
Pokekachu-1.0.1.dist-info/top_level.txt
Pokekachu-1.0.1.dist-info/RECORD
