Metadata-Version: 2.1
Name: Pokekachu
Version: 1.0.1
Summary: Librerias paran generar un Pokemon aleatorio
Author: Maria Martinez
Author-email: 202224015_martinez@tesch.edu.mx
Requires-Dist: pandas
